[
  {
    "brand": "MG",
    "model": "MG",
    "variant": "MG Cyberster GT AWD",
    "generation": "Cyberster",
    "year_start": 2024,
    "year_end": null,
    "engine_type": null,
    "displacement_cc": null,
    "cylinders": null,
    "power_hp": 510,
    "power_kw": 77,
    "torque_nm": null,
    "acceleration_0_100": null,
    "top_speed_kmh": null,
    "length_mm": null,
    "width_mm": null,
    "height_mm": null,
    "wheelbase_mm": null,
    "trunk_volume_l": null,
    "curb_weight_kg": null,
    "drivetrain": null,
    "transmission": null,
    "fuel_consumption_l100km": null,
    "co2_gkm": null,
    "source_url": "https://www.ultimatespecs.com/car-specs/MG/139505/MG-Cyberster-GT-AWD.html",
    "scraped_at": "2026-01-30T06:46:39.335Z"
  },
  {
    "brand": "MG",
    "model": "MG",
    "variant": "MG Cyberster Trophy RWD",
    "generation": "Cyberster",
    "year_start": 2024,
    "year_end": null,
    "engine_type": null,
    "displacement_cc": null,
    "cylinders": null,
    "power_hp": 340,
    "power_kw": 77,
    "torque_nm": null,
    "acceleration_0_100": null,
    "top_speed_kmh": null,
    "length_mm": null,
    "width_mm": null,
    "height_mm": null,
    "wheelbase_mm": null,
    "trunk_volume_l": null,
    "curb_weight_kg": null,
    "drivetrain": null,
    "transmission": null,
    "fuel_consumption_l100km": null,
    "co2_gkm": null,
    "source_url": "https://www.ultimatespecs.com/car-specs/MG/139506/MG-Cyberster-Trophy-RWD.html",
    "scraped_at": "2026-01-30T06:46:39.335Z"
  },
  {
    "brand": "MG",
    "model": "MG",
    "variant": "MG 3 1.5",
    "generation": "3",
    "year_start": 2025,
    "year_end": null,
    "engine_type": null,
    "displacement_cc": null,
    "cylinders": null,
    "power_hp": 116,
    "power_kw": 116,
    "torque_nm": null,
    "acceleration_0_100": null,
    "top_speed_kmh": null,
    "length_mm": null,
    "width_mm": null,
    "height_mm": null,
    "wheelbase_mm": null,
    "trunk_volume_l": null,
    "curb_weight_kg": null,
    "drivetrain": null,
    "transmission": null,
    "fuel_consumption_l100km": null,
    "co2_gkm": null,
    "source_url": "https://www.ultimatespecs.com/car-specs/MG/146991/MG-3-15.html",
    "scraped_at": "2026-01-30T06:46:40.467Z"
  },
  {
    "brand": "MG",
    "model": "MG",
    "variant": "MG 3 Hybrid+",
    "generation": "3",
    "year_start": 2024,
    "year_end": null,
    "engine_type": null,
    "displacement_cc": null,
    "cylinders": null,
    "power_hp": 194,
    "power_kw": 194,
    "torque_nm": null,
    "acceleration_0_100": null,
    "top_speed_kmh": null,
    "length_mm": null,
    "width_mm": null,
    "height_mm": null,
    "wheelbase_mm": null,
    "trunk_volume_l": null,
    "curb_weight_kg": null,
    "drivetrain": null,
    "transmission": null,
    "fuel_consumption_l100km": null,
    "co2_gkm": null,
    "source_url": "https://www.ultimatespecs.com/car-specs/MG/138068/MG-3-Hybrid+.html",
    "scraped_at": "2026-01-30T06:46:40.468Z"
  },
  {
    "brand": "MG",
    "model": "MG",
    "variant": "MG 4 EV Extended Range Trophy",
    "generation": "4-EV",
    "year_start": 2023,
    "year_end": null,
    "engine_type": null,
    "displacement_cc": null,
    "cylinders": null,
    "power_hp": 245,
    "power_kw": 77,
    "torque_nm": null,
    "acceleration_0_100": null,
    "top_speed_kmh": null,
    "length_mm": null,
    "width_mm": null,
    "height_mm": null,
    "wheelbase_mm": null,
    "trunk_volume_l": null,
    "curb_weight_kg": null,
    "drivetrain": null,
    "transmission": null,
    "fuel_consumption_l100km": null,
    "co2_gkm": null,
    "source_url": "https://www.ultimatespecs.com/car-specs/MG/136773/MG-4-EV-Extended-Range-Trophy.html",
    "scraped_at": "2026-01-30T06:46:41.544Z"
  },
  {
    "brand": "MG",
    "model": "MG",
    "variant": "MG 4 EV Maximum Range Comfort",
    "generation": "4-EV",
    "year_start": 2022,
    "year_end": null,
    "engine_type": null,
    "displacement_cc": null,
    "cylinders": null,
    "power_hp": 204,
    "power_kw": 64,
    "torque_nm": null,
    "acceleration_0_100": null,
    "top_speed_kmh": null,
    "length_mm": null,
    "width_mm": null,
    "height_mm": null,
    "wheelbase_mm": null,
    "trunk_volume_l": null,
    "curb_weight_kg": null,
    "drivetrain": null,
    "transmission": null,
    "fuel_consumption_l100km": null,
    "co2_gkm": null,
    "source_url": "https://www.ultimatespecs.com/car-specs/MG/133845/MG-4-EV-Maximum-Range-Comfort.html",
    "scraped_at": "2026-01-30T06:46:41.544Z"
  },
  {
    "brand": "MG",
    "model": "MG",
    "variant": "MG 4 EV Maximum Range Luxury",
    "generation": "4-EV",
    "year_start": 2022,
    "year_end": null,
    "engine_type": null,
    "displacement_cc": null,
    "cylinders": null,
    "power_hp": 204,
    "power_kw": 64,
    "torque_nm": null,
    "acceleration_0_100": null,
    "top_speed_kmh": null,
    "length_mm": null,
    "width_mm": null,
    "height_mm": null,
    "wheelbase_mm": null,
    "trunk_volume_l": null,
    "curb_weight_kg": null,
    "drivetrain": null,
    "transmission": null,
    "fuel_consumption_l100km": null,
    "co2_gkm": null,
    "source_url": "https://www.ultimatespecs.com/car-specs/MG/133846/MG-4-EV-Maximum-Range-Luxury.html",
    "scraped_at": "2026-01-30T06:46:41.544Z"
  },
  {
    "brand": "MG",
    "model": "MG",
    "variant": "MG 4 EV Standard Range",
    "generation": "4-EV",
    "year_start": 2022,
    "year_end": null,
    "engine_type": null,
    "displacement_cc": null,
    "cylinders": null,
    "power_hp": 170,
    "power_kw": 51,
    "torque_nm": null,
    "acceleration_0_100": null,
    "top_speed_kmh": null,
    "length_mm": null,
    "width_mm": null,
    "height_mm": null,
    "wheelbase_mm": null,
    "trunk_volume_l": null,
    "curb_weight_kg": null,
    "drivetrain": null,
    "transmission": null,
    "fuel_consumption_l100km": null,
    "co2_gkm": null,
    "source_url": "https://www.ultimatespecs.com/car-specs/MG/133844/MG-4-EV-Standard-Range.html",
    "scraped_at": "2026-01-30T06:46:41.544Z"
  },
  {
    "brand": "MG",
    "model": "MG",
    "variant": "MG 4 EV XPower 64 kWh",
    "generation": "4-EV",
    "year_start": 2023,
    "year_end": null,
    "engine_type": null,
    "displacement_cc": null,
    "cylinders": null,
    "power_hp": 435,
    "power_kw": 64,
    "torque_nm": null,
    "acceleration_0_100": null,
    "top_speed_kmh": null,
    "length_mm": null,
    "width_mm": null,
    "height_mm": null,
    "wheelbase_mm": null,
    "trunk_volume_l": null,
    "curb_weight_kg": null,
    "drivetrain": null,
    "transmission": null,
    "fuel_consumption_l100km": null,
    "co2_gkm": null,
    "source_url": "https://www.ultimatespecs.com/car-specs/MG/136412/MG-4-EV-XPower-64-kWh.html",
    "scraped_at": "2026-01-30T06:46:41.544Z"
  },
  {
    "brand": "MG",
    "model": "MG",
    "variant": "MGS5 EV Long Range Comfort",
    "generation": "MGS5-EV",
    "year_start": 2025,
    "year_end": null,
    "engine_type": null,
    "displacement_cc": null,
    "cylinders": null,
    "power_hp": 231,
    "power_kw": 64,
    "torque_nm": null,
    "acceleration_0_100": null,
    "top_speed_kmh": null,
    "length_mm": null,
    "width_mm": null,
    "height_mm": null,
    "wheelbase_mm": null,
    "trunk_volume_l": null,
    "curb_weight_kg": null,
    "drivetrain": null,
    "transmission": null,
    "fuel_consumption_l100km": null,
    "co2_gkm": null,
    "source_url": "https://www.ultimatespecs.com/car-specs/MG/150393/MG-MGS5-EV-Long-Range-Comfort.html",
    "scraped_at": "2026-01-30T06:46:42.749Z"
  },
  {
    "brand": "MG",
    "model": "MG",
    "variant": "MGS5 EV Long Range Luxury",
    "generation": "MGS5-EV",
    "year_start": 2025,
    "year_end": null,
    "engine_type": null,
    "displacement_cc": null,
    "cylinders": null,
    "power_hp": 231,
    "power_kw": 64,
    "torque_nm": null,
    "acceleration_0_100": null,
    "top_speed_kmh": null,
    "length_mm": null,
    "width_mm": null,
    "height_mm": null,
    "wheelbase_mm": null,
    "trunk_volume_l": null,
    "curb_weight_kg": null,
    "drivetrain": null,
    "transmission": null,
    "fuel_consumption_l100km": null,
    "co2_gkm": null,
    "source_url": "https://www.ultimatespecs.com/car-specs/MG/150392/MG-MGS5-EV-Long-Range-Luxury.html",
    "scraped_at": "2026-01-30T06:46:42.749Z"
  },
  {
    "brand": "MG",
    "model": "MG",
    "variant": "MGS5 EV Standard Range Comfort",
    "generation": "MGS5-EV",
    "year_start": 2025,
    "year_end": null,
    "engine_type": null,
    "displacement_cc": null,
    "cylinders": null,
    "power_hp": 170,
    "power_kw": 49,
    "torque_nm": null,
    "acceleration_0_100": null,
    "top_speed_kmh": null,
    "length_mm": null,
    "width_mm": null,
    "height_mm": null,
    "wheelbase_mm": null,
    "trunk_volume_l": null,
    "curb_weight_kg": null,
    "drivetrain": null,
    "transmission": null,
    "fuel_consumption_l100km": null,
    "co2_gkm": null,
    "source_url": "https://www.ultimatespecs.com/car-specs/MG/150394/MG-MGS5-EV-Standard-Range-Comfort.html",
    "scraped_at": "2026-01-30T06:46:42.749Z"
  },
  {
    "brand": "MG",
    "model": "MG",
    "variant": "MG 5 SW EV Long Range",
    "generation": "5-SW-EV",
    "year_start": 2022,
    "year_end": null,
    "engine_type": null,
    "displacement_cc": null,
    "cylinders": null,
    "power_hp": 177,
    "power_kw": 61.1,
    "torque_nm": null,
    "acceleration_0_100": null,
    "top_speed_kmh": null,
    "length_mm": null,
    "width_mm": null,
    "height_mm": null,
    "wheelbase_mm": null,
    "trunk_volume_l": null,
    "curb_weight_kg": null,
    "drivetrain": null,
    "transmission": null,
    "fuel_consumption_l100km": null,
    "co2_gkm": null,
    "source_url": "https://www.ultimatespecs.com/car-specs/MG/131296/MG-5-SW-EV-Long-Range.html",
    "scraped_at": "2026-01-30T06:46:43.821Z"
  },
  {
    "brand": "MG",
    "model": "MG",
    "variant": "MG 5 SW EV Standard Range",
    "generation": "5-SW-EV",
    "year_start": 2022,
    "year_end": null,
    "engine_type": null,
    "displacement_cc": null,
    "cylinders": null,
    "power_hp": 177,
    "power_kw": 50.3,
    "torque_nm": null,
    "acceleration_0_100": null,
    "top_speed_kmh": null,
    "length_mm": null,
    "width_mm": null,
    "height_mm": null,
    "wheelbase_mm": null,
    "trunk_volume_l": null,
    "curb_weight_kg": null,
    "drivetrain": null,
    "transmission": null,
    "fuel_consumption_l100km": null,
    "co2_gkm": null,
    "source_url": "https://www.ultimatespecs.com/car-specs/MG/131295/MG-5-SW-EV-Standard-Range.html",
    "scraped_at": "2026-01-30T06:46:43.821Z"
  },
  {
    "brand": "MG",
    "model": "MG",
    "variant": "MG Marvel R 180HP RWD",
    "generation": "Marvel-R",
    "year_start": 2021,
    "year_end": null,
    "engine_type": null,
    "displacement_cc": null,
    "cylinders": null,
    "power_hp": 180,
    "power_kw": 69.9,
    "torque_nm": null,
    "acceleration_0_100": null,
    "top_speed_kmh": null,
    "length_mm": null,
    "width_mm": null,
    "height_mm": null,
    "wheelbase_mm": null,
    "trunk_volume_l": null,
    "curb_weight_kg": null,
    "drivetrain": null,
    "transmission": null,
    "fuel_consumption_l100km": null,
    "co2_gkm": null,
    "source_url": "https://www.ultimatespecs.com/car-specs/MG/128222/MG-Marvel-R-180HP-RWD.html",
    "scraped_at": "2026-01-30T06:46:44.889Z"
  },
  {
    "brand": "MG",
    "model": "MG",
    "variant": "MG Marvel R 290HP AWD Performance",
    "generation": "Marvel-R",
    "year_start": 2021,
    "year_end": null,
    "engine_type": null,
    "displacement_cc": null,
    "cylinders": null,
    "power_hp": 288,
    "power_kw": 69.9,
    "torque_nm": null,
    "acceleration_0_100": null,
    "top_speed_kmh": null,
    "length_mm": null,
    "width_mm": null,
    "height_mm": null,
    "wheelbase_mm": null,
    "trunk_volume_l": null,
    "curb_weight_kg": null,
    "drivetrain": null,
    "transmission": null,
    "fuel_consumption_l100km": null,
    "co2_gkm": null,
    "source_url": "https://www.ultimatespecs.com/car-specs/MG/128224/MG-Marvel-R-290HP-AWD-Performance.html",
    "scraped_at": "2026-01-30T06:46:44.889Z"
  },
  {
    "brand": "MG",
    "model": "MG",
    "variant": "MG ZR 105",
    "generation": "ZR",
    "year_start": 2001,
    "year_end": null,
    "engine_type": null,
    "displacement_cc": null,
    "cylinders": null,
    "power_hp": 103,
    "power_kw": 103,
    "torque_nm": null,
    "acceleration_0_100": null,
    "top_speed_kmh": null,
    "length_mm": null,
    "width_mm": null,
    "height_mm": null,
    "wheelbase_mm": null,
    "trunk_volume_l": null,
    "curb_weight_kg": null,
    "drivetrain": null,
    "transmission": null,
    "fuel_consumption_l100km": null,
    "co2_gkm": null,
    "source_url": "https://www.ultimatespecs.com/car-specs/MG/6851/MG-ZR-105.html",
    "scraped_at": "2026-01-30T06:46:45.975Z"
  },
  {
    "brand": "MG",
    "model": "MG",
    "variant": "MG ZR 105",
    "generation": "ZR",
    "year_start": 2004,
    "year_end": null,
    "engine_type": null,
    "displacement_cc": null,
    "cylinders": null,
    "power_hp": 103,
    "power_kw": 103,
    "torque_nm": null,
    "acceleration_0_100": null,
    "top_speed_kmh": null,
    "length_mm": null,
    "width_mm": null,
    "height_mm": null,
    "wheelbase_mm": null,
    "trunk_volume_l": null,
    "curb_weight_kg": null,
    "drivetrain": null,
    "transmission": null,
    "fuel_consumption_l100km": null,
    "co2_gkm": null,
    "source_url": "https://www.ultimatespecs.com/car-specs/MG/6856/MG-ZR-105.html",
    "scraped_at": "2026-01-30T06:46:45.976Z"
  },
  {
    "brand": "MG",
    "model": "MG",
    "variant": "MG ZR 160",
    "generation": "ZR",
    "year_start": 2001,
    "year_end": null,
    "engine_type": null,
    "displacement_cc": null,
    "cylinders": null,
    "power_hp": 160,
    "power_kw": 160,
    "torque_nm": null,
    "acceleration_0_100": null,
    "top_speed_kmh": null,
    "length_mm": null,
    "width_mm": null,
    "height_mm": null,
    "wheelbase_mm": null,
    "trunk_volume_l": null,
    "curb_weight_kg": null,
    "drivetrain": null,
    "transmission": null,
    "fuel_consumption_l100km": null,
    "co2_gkm": null,
    "source_url": "https://www.ultimatespecs.com/car-specs/MG/6852/MG-ZR-160.html",
    "scraped_at": "2026-01-30T06:46:45.976Z"
  },
  {
    "brand": "MG",
    "model": "MG",
    "variant": "MG ZR 160",
    "generation": "ZR",
    "year_start": 2004,
    "year_end": null,
    "engine_type": null,
    "displacement_cc": null,
    "cylinders": null,
    "power_hp": 160,
    "power_kw": 160,
    "torque_nm": null,
    "acceleration_0_100": null,
    "top_speed_kmh": null,
    "length_mm": null,
    "width_mm": null,
    "height_mm": null,
    "wheelbase_mm": null,
    "trunk_volume_l": null,
    "curb_weight_kg": null,
    "drivetrain": null,
    "transmission": null,
    "fuel_consumption_l100km": null,
    "co2_gkm": null,
    "source_url": "https://www.ultimatespecs.com/car-specs/MG/6855/MG-ZR-160.html",
    "scraped_at": "2026-01-30T06:46:45.976Z"
  },
  {
    "brand": "MG",
    "model": "MG",
    "variant": "MG ZR 100 IDT",
    "generation": "ZR",
    "year_start": 2002,
    "year_end": null,
    "engine_type": null,
    "displacement_cc": null,
    "cylinders": null,
    "power_hp": 101,
    "power_kw": 101,
    "torque_nm": null,
    "acceleration_0_100": null,
    "top_speed_kmh": null,
    "length_mm": null,
    "width_mm": null,
    "height_mm": null,
    "wheelbase_mm": null,
    "trunk_volume_l": null,
    "curb_weight_kg": null,
    "drivetrain": null,
    "transmission": null,
    "fuel_consumption_l100km": null,
    "co2_gkm": null,
    "source_url": "https://www.ultimatespecs.com/car-specs/MG/6853/MG-ZR-100-IDT.html",
    "scraped_at": "2026-01-30T06:46:45.976Z"
  },
  {
    "brand": "MG",
    "model": "MG",
    "variant": "MG ZR 115 IDT",
    "generation": "ZR",
    "year_start": 2003,
    "year_end": null,
    "engine_type": null,
    "displacement_cc": null,
    "cylinders": null,
    "power_hp": 113,
    "power_kw": 113,
    "torque_nm": null,
    "acceleration_0_100": null,
    "top_speed_kmh": null,
    "length_mm": null,
    "width_mm": null,
    "height_mm": null,
    "wheelbase_mm": null,
    "trunk_volume_l": null,
    "curb_weight_kg": null,
    "drivetrain": null,
    "transmission": null,
    "fuel_consumption_l100km": null,
    "co2_gkm": null,
    "source_url": "https://www.ultimatespecs.com/car-specs/MG/6857/MG-ZR-115-IDT.html",
    "scraped_at": "2026-01-30T06:46:45.976Z"
  },
  {
    "brand": "MG",
    "model": "MG",
    "variant": "MG ZR 115 IDT",
    "generation": "ZR",
    "year_start": 2004,
    "year_end": null,
    "engine_type": null,
    "displacement_cc": null,
    "cylinders": null,
    "power_hp": 113,
    "power_kw": 113,
    "torque_nm": null,
    "acceleration_0_100": null,
    "top_speed_kmh": null,
    "length_mm": null,
    "width_mm": null,
    "height_mm": null,
    "wheelbase_mm": null,
    "trunk_volume_l": null,
    "curb_weight_kg": null,
    "drivetrain": null,
    "transmission": null,
    "fuel_consumption_l100km": null,
    "co2_gkm": null,
    "source_url": "https://www.ultimatespecs.com/car-specs/MG/6854/MG-ZR-115-IDT.html",
    "scraped_at": "2026-01-30T06:46:45.976Z"
  },
  {
    "brand": "MG",
    "model": "MG",
    "variant": "MG ZT 160",
    "generation": "ZT",
    "year_start": 2002,
    "year_end": null,
    "engine_type": null,
    "displacement_cc": null,
    "cylinders": null,
    "power_hp": 160,
    "power_kw": 160,
    "torque_nm": null,
    "acceleration_0_100": null,
    "top_speed_kmh": null,
    "length_mm": null,
    "width_mm": null,
    "height_mm": null,
    "wheelbase_mm": null,
    "trunk_volume_l": null,
    "curb_weight_kg": null,
    "drivetrain": null,
    "transmission": null,
    "fuel_consumption_l100km": null,
    "co2_gkm": null,
    "source_url": "https://www.ultimatespecs.com/car-specs/MG/6880/MG-ZT-160.html",
    "scraped_at": "2026-01-30T06:46:47.041Z"
  },
  {
    "brand": "MG",
    "model": "MG",
    "variant": "MG ZT 160",
    "generation": "ZT",
    "year_start": 2004,
    "year_end": null,
    "engine_type": null,
    "displacement_cc": null,
    "cylinders": null,
    "power_hp": 160,
    "power_kw": 160,
    "torque_nm": null,
    "acceleration_0_100": null,
    "top_speed_kmh": null,
    "length_mm": null,
    "width_mm": null,
    "height_mm": null,
    "wheelbase_mm": null,
    "trunk_volume_l": null,
    "curb_weight_kg": null,
    "drivetrain": null,
    "transmission": null,
    "fuel_consumption_l100km": null,
    "co2_gkm": null,
    "source_url": "https://www.ultimatespecs.com/car-specs/MG/6876/MG-ZT-160.html",
    "scraped_at": "2026-01-30T06:46:47.041Z"
  },
  {
    "brand": "MG",
    "model": "MG",
    "variant": "MG ZT 180",
    "generation": "ZT",
    "year_start": 2002,
    "year_end": null,
    "engine_type": null,
    "displacement_cc": null,
    "cylinders": null,
    "power_hp": 177,
    "power_kw": 177,
    "torque_nm": null,
    "acceleration_0_100": null,
    "top_speed_kmh": null,
    "length_mm": null,
    "width_mm": null,
    "height_mm": null,
    "wheelbase_mm": null,
    "trunk_volume_l": null,
    "curb_weight_kg": null,
    "drivetrain": null,
    "transmission": null,
    "fuel_consumption_l100km": null,
    "co2_gkm": null,
    "source_url": "https://www.ultimatespecs.com/car-specs/MG/6878/MG-ZT-180.html",
    "scraped_at": "2026-01-30T06:46:47.041Z"
  },
  {
    "brand": "MG",
    "model": "MG",
    "variant": "MG ZT 180",
    "generation": "ZT",
    "year_start": 2004,
    "year_end": null,
    "engine_type": null,
    "displacement_cc": null,
    "cylinders": null,
    "power_hp": 177,
    "power_kw": 177,
    "torque_nm": null,
    "acceleration_0_100": null,
    "top_speed_kmh": null,
    "length_mm": null,
    "width_mm": null,
    "height_mm": null,
    "wheelbase_mm": null,
    "trunk_volume_l": null,
    "curb_weight_kg": null,
    "drivetrain": null,
    "transmission": null,
    "fuel_consumption_l100km": null,
    "co2_gkm": null,
    "source_url": "https://www.ultimatespecs.com/car-specs/MG/6874/MG-ZT-180.html",
    "scraped_at": "2026-01-30T06:46:47.041Z"
  },
  {
    "brand": "MG",
    "model": "MG",
    "variant": "MG ZT 190",
    "generation": "ZT",
    "year_start": 2001,
    "year_end": null,
    "engine_type": null,
    "displacement_cc": null,
    "cylinders": null,
    "power_hp": 190,
    "power_kw": 190,
    "torque_nm": null,
    "acceleration_0_100": null,
    "top_speed_kmh": null,
    "length_mm": null,
    "width_mm": null,
    "height_mm": null,
    "wheelbase_mm": null,
    "trunk_volume_l": null,
    "curb_weight_kg": null,
    "drivetrain": null,
    "transmission": null,
    "fuel_consumption_l100km": null,
    "co2_gkm": null,
    "source_url": "https://www.ultimatespecs.com/car-specs/MG/6879/MG-ZT-190.html",
    "scraped_at": "2026-01-30T06:46:47.041Z"
  },
  {
    "brand": "MG",
    "model": "MG",
    "variant": "MG ZT 190",
    "generation": "ZT",
    "year_start": 2004,
    "year_end": null,
    "engine_type": null,
    "displacement_cc": null,
    "cylinders": null,
    "power_hp": 190,
    "power_kw": 190,
    "torque_nm": null,
    "acceleration_0_100": null,
    "top_speed_kmh": null,
    "length_mm": null,
    "width_mm": null,
    "height_mm": null,
    "wheelbase_mm": null,
    "trunk_volume_l": null,
    "curb_weight_kg": null,
    "drivetrain": null,
    "transmission": null,
    "fuel_consumption_l100km": null,
    "co2_gkm": null,
    "source_url": "https://www.ultimatespecs.com/car-specs/MG/6875/MG-ZT-190.html",
    "scraped_at": "2026-01-30T06:46:47.041Z"
  },
  {
    "brand": "MG",
    "model": "MG",
    "variant": "MG ZT 260",
    "generation": "ZT",
    "year_start": 2004,
    "year_end": null,
    "engine_type": null,
    "displacement_cc": null,
    "cylinders": null,
    "power_hp": 260,
    "power_kw": 260,
    "torque_nm": null,
    "acceleration_0_100": null,
    "top_speed_kmh": null,
    "length_mm": null,
    "width_mm": null,
    "height_mm": null,
    "wheelbase_mm": null,
    "trunk_volume_l": null,
    "curb_weight_kg": null,
    "drivetrain": null,
    "transmission": null,
    "fuel_consumption_l100km": null,
    "co2_gkm": null,
    "source_url": "https://www.ultimatespecs.com/car-specs/MG/6873/MG-ZT-260.html",
    "scraped_at": "2026-01-30T06:46:47.041Z"
  },
  {
    "brand": "MG",
    "model": "MG",
    "variant": "MG ZT 135 CDTI",
    "generation": "ZT",
    "year_start": 2003,
    "year_end": null,
    "engine_type": null,
    "displacement_cc": null,
    "cylinders": null,
    "power_hp": 131,
    "power_kw": 131,
    "torque_nm": null,
    "acceleration_0_100": null,
    "top_speed_kmh": null,
    "length_mm": null,
    "width_mm": null,
    "height_mm": null,
    "wheelbase_mm": null,
    "trunk_volume_l": null,
    "curb_weight_kg": null,
    "drivetrain": null,
    "transmission": null,
    "fuel_consumption_l100km": null,
    "co2_gkm": null,
    "source_url": "https://www.ultimatespecs.com/car-specs/MG/6877/MG-ZT-135-CDTI.html",
    "scraped_at": "2026-01-30T06:46:47.041Z"
  },
  {
    "brand": "MG",
    "model": "MG",
    "variant": "MG ZT 135 CDTI",
    "generation": "ZT",
    "year_start": 2004,
    "year_end": null,
    "engine_type": null,
    "displacement_cc": null,
    "cylinders": null,
    "power_hp": 131,
    "power_kw": 131,
    "torque_nm": null,
    "acceleration_0_100": null,
    "top_speed_kmh": null,
    "length_mm": null,
    "width_mm": null,
    "height_mm": null,
    "wheelbase_mm": null,
    "trunk_volume_l": null,
    "curb_weight_kg": null,
    "drivetrain": null,
    "transmission": null,
    "fuel_consumption_l100km": null,
    "co2_gkm": null,
    "source_url": "https://www.ultimatespecs.com/car-specs/MG/6872/MG-ZT-135-CDTI.html",
    "scraped_at": "2026-01-30T06:46:47.041Z"
  },
  {
    "brand": "MG",
    "model": "MG",
    "variant": "MG ZT T 160",
    "generation": "ZT-T",
    "year_start": 2002,
    "year_end": null,
    "engine_type": null,
    "displacement_cc": null,
    "cylinders": null,
    "power_hp": 160,
    "power_kw": 160,
    "torque_nm": null,
    "acceleration_0_100": null,
    "top_speed_kmh": null,
    "length_mm": null,
    "width_mm": null,
    "height_mm": null,
    "wheelbase_mm": null,
    "trunk_volume_l": null,
    "curb_weight_kg": null,
    "drivetrain": null,
    "transmission": null,
    "fuel_consumption_l100km": null,
    "co2_gkm": null,
    "source_url": "https://www.ultimatespecs.com/car-specs/MG/6889/MG-ZT-T-160.html",
    "scraped_at": "2026-01-30T06:46:48.157Z"
  },
  {
    "brand": "MG",
    "model": "MG",
    "variant": "MG ZT T 160",
    "generation": "ZT-T",
    "year_start": 2004,
    "year_end": null,
    "engine_type": null,
    "displacement_cc": null,
    "cylinders": null,
    "power_hp": 160,
    "power_kw": 160,
    "torque_nm": null,
    "acceleration_0_100": null,
    "top_speed_kmh": null,
    "length_mm": null,
    "width_mm": null,
    "height_mm": null,
    "wheelbase_mm": null,
    "trunk_volume_l": null,
    "curb_weight_kg": null,
    "drivetrain": null,
    "transmission": null,
    "fuel_consumption_l100km": null,
    "co2_gkm": null,
    "source_url": "https://www.ultimatespecs.com/car-specs/MG/6885/MG-ZT-T-160.html",
    "scraped_at": "2026-01-30T06:46:48.157Z"
  },
  {
    "brand": "MG",
    "model": "MG",
    "variant": "MG ZT T 180",
    "generation": "ZT-T",
    "year_start": 2002,
    "year_end": null,
    "engine_type": null,
    "displacement_cc": null,
    "cylinders": null,
    "power_hp": 177,
    "power_kw": 177,
    "torque_nm": null,
    "acceleration_0_100": null,
    "top_speed_kmh": null,
    "length_mm": null,
    "width_mm": null,
    "height_mm": null,
    "wheelbase_mm": null,
    "trunk_volume_l": null,
    "curb_weight_kg": null,
    "drivetrain": null,
    "transmission": null,
    "fuel_consumption_l100km": null,
    "co2_gkm": null,
    "source_url": "https://www.ultimatespecs.com/car-specs/MG/6887/MG-ZT-T-180.html",
    "scraped_at": "2026-01-30T06:46:48.157Z"
  },
  {
    "brand": "MG",
    "model": "MG",
    "variant": "MG ZT T 180",
    "generation": "ZT-T",
    "year_start": 2004,
    "year_end": null,
    "engine_type": null,
    "displacement_cc": null,
    "cylinders": null,
    "power_hp": 177,
    "power_kw": 177,
    "torque_nm": null,
    "acceleration_0_100": null,
    "top_speed_kmh": null,
    "length_mm": null,
    "width_mm": null,
    "height_mm": null,
    "wheelbase_mm": null,
    "trunk_volume_l": null,
    "curb_weight_kg": null,
    "drivetrain": null,
    "transmission": null,
    "fuel_consumption_l100km": null,
    "co2_gkm": null,
    "source_url": "https://www.ultimatespecs.com/car-specs/MG/6883/MG-ZT-T-180.html",
    "scraped_at": "2026-01-30T06:46:48.157Z"
  },
  {
    "brand": "MG",
    "model": "MG",
    "variant": "MG ZT T 190",
    "generation": "ZT-T",
    "year_start": 2001,
    "year_end": null,
    "engine_type": null,
    "displacement_cc": null,
    "cylinders": null,
    "power_hp": 190,
    "power_kw": 190,
    "torque_nm": null,
    "acceleration_0_100": null,
    "top_speed_kmh": null,
    "length_mm": null,
    "width_mm": null,
    "height_mm": null,
    "wheelbase_mm": null,
    "trunk_volume_l": null,
    "curb_weight_kg": null,
    "drivetrain": null,
    "transmission": null,
    "fuel_consumption_l100km": null,
    "co2_gkm": null,
    "source_url": "https://www.ultimatespecs.com/car-specs/MG/6888/MG-ZT-T-190.html",
    "scraped_at": "2026-01-30T06:46:48.157Z"
  },
  {
    "brand": "MG",
    "model": "MG",
    "variant": "MG ZT T 190",
    "generation": "ZT-T",
    "year_start": 2004,
    "year_end": null,
    "engine_type": null,
    "displacement_cc": null,
    "cylinders": null,
    "power_hp": 190,
    "power_kw": 190,
    "torque_nm": null,
    "acceleration_0_100": null,
    "top_speed_kmh": null,
    "length_mm": null,
    "width_mm": null,
    "height_mm": null,
    "wheelbase_mm": null,
    "trunk_volume_l": null,
    "curb_weight_kg": null,
    "drivetrain": null,
    "transmission": null,
    "fuel_consumption_l100km": null,
    "co2_gkm": null,
    "source_url": "https://www.ultimatespecs.com/car-specs/MG/6884/MG-ZT-T-190.html",
    "scraped_at": "2026-01-30T06:46:48.157Z"
  },
  {
    "brand": "MG",
    "model": "MG",
    "variant": "MG ZT T 260",
    "generation": "ZT-T",
    "year_start": 2004,
    "year_end": null,
    "engine_type": null,
    "displacement_cc": null,
    "cylinders": null,
    "power_hp": 260,
    "power_kw": 260,
    "torque_nm": null,
    "acceleration_0_100": null,
    "top_speed_kmh": null,
    "length_mm": null,
    "width_mm": null,
    "height_mm": null,
    "wheelbase_mm": null,
    "trunk_volume_l": null,
    "curb_weight_kg": null,
    "drivetrain": null,
    "transmission": null,
    "fuel_consumption_l100km": null,
    "co2_gkm": null,
    "source_url": "https://www.ultimatespecs.com/car-specs/MG/6882/MG-ZT-T-260.html",
    "scraped_at": "2026-01-30T06:46:48.157Z"
  },
  {
    "brand": "MG",
    "model": "MG",
    "variant": "MG ZT T 135 CDTI",
    "generation": "ZT-T",
    "year_start": 2003,
    "year_end": null,
    "engine_type": null,
    "displacement_cc": null,
    "cylinders": null,
    "power_hp": 131,
    "power_kw": 131,
    "torque_nm": null,
    "acceleration_0_100": null,
    "top_speed_kmh": null,
    "length_mm": null,
    "width_mm": null,
    "height_mm": null,
    "wheelbase_mm": null,
    "trunk_volume_l": null,
    "curb_weight_kg": null,
    "drivetrain": null,
    "transmission": null,
    "fuel_consumption_l100km": null,
    "co2_gkm": null,
    "source_url": "https://www.ultimatespecs.com/car-specs/MG/6886/MG-ZT-T-135-CDTI.html",
    "scraped_at": "2026-01-30T06:46:48.157Z"
  },
  {
    "brand": "MG",
    "model": "MG",
    "variant": "MG ZT T 135 CDTI",
    "generation": "ZT-T",
    "year_start": 2004,
    "year_end": null,
    "engine_type": null,
    "displacement_cc": null,
    "cylinders": null,
    "power_hp": 131,
    "power_kw": 131,
    "torque_nm": null,
    "acceleration_0_100": null,
    "top_speed_kmh": null,
    "length_mm": null,
    "width_mm": null,
    "height_mm": null,
    "wheelbase_mm": null,
    "trunk_volume_l": null,
    "curb_weight_kg": null,
    "drivetrain": null,
    "transmission": null,
    "fuel_consumption_l100km": null,
    "co2_gkm": null,
    "source_url": "https://www.ultimatespecs.com/car-specs/MG/6881/MG-ZT-T-135-CDTI.html",
    "scraped_at": "2026-01-30T06:46:48.157Z"
  },
  {
    "brand": "MG",
    "model": "MG",
    "variant": "MG F 1.8i",
    "generation": "F",
    "year_start": 1996,
    "year_end": null,
    "engine_type": null,
    "displacement_cc": null,
    "cylinders": null,
    "power_hp": 120,
    "power_kw": 120,
    "torque_nm": null,
    "acceleration_0_100": null,
    "top_speed_kmh": null,
    "length_mm": null,
    "width_mm": null,
    "height_mm": null,
    "wheelbase_mm": null,
    "trunk_volume_l": null,
    "curb_weight_kg": null,
    "drivetrain": null,
    "transmission": null,
    "fuel_consumption_l100km": null,
    "co2_gkm": null,
    "source_url": "https://www.ultimatespecs.com/car-specs/MG/6845/MG-F-18i.html",
    "scraped_at": "2026-01-30T06:46:49.227Z"
  },
  {
    "brand": "MG",
    "model": "MG",
    "variant": "MG F 1.8i 75th Anniversary Edition",
    "generation": "F",
    "year_start": 1999,
    "year_end": null,
    "engine_type": null,
    "displacement_cc": null,
    "cylinders": null,
    "power_hp": 120,
    "power_kw": 120,
    "torque_nm": null,
    "acceleration_0_100": null,
    "top_speed_kmh": null,
    "length_mm": null,
    "width_mm": null,
    "height_mm": null,
    "wheelbase_mm": null,
    "trunk_volume_l": null,
    "curb_weight_kg": null,
    "drivetrain": null,
    "transmission": null,
    "fuel_consumption_l100km": null,
    "co2_gkm": null,
    "source_url": "https://www.ultimatespecs.com/car-specs/MG/6844/MG-F-18i-75th-Anniversary-Edition.html",
    "scraped_at": "2026-01-30T06:46:49.227Z"
  },
  {
    "brand": "MG",
    "model": "MG",
    "variant": "MG F 1.8i VVC",
    "generation": "F",
    "year_start": 1996,
    "year_end": null,
    "engine_type": null,
    "displacement_cc": null,
    "cylinders": null,
    "power_hp": 145,
    "power_kw": 145,
    "torque_nm": null,
    "acceleration_0_100": null,
    "top_speed_kmh": null,
    "length_mm": null,
    "width_mm": null,
    "height_mm": null,
    "wheelbase_mm": null,
    "trunk_volume_l": null,
    "curb_weight_kg": null,
    "drivetrain": null,
    "transmission": null,
    "fuel_consumption_l100km": null,
    "co2_gkm": null,
    "source_url": "https://www.ultimatespecs.com/car-specs/MG/6843/MG-F-18i-VVC.html",
    "scraped_at": "2026-01-30T06:46:49.227Z"
  },
  {
    "brand": "MG",
    "model": "MG",
    "variant": "MG F 160",
    "generation": "F",
    "year_start": 2001,
    "year_end": null,
    "engine_type": null,
    "displacement_cc": null,
    "cylinders": null,
    "power_hp": 160,
    "power_kw": 160,
    "torque_nm": null,
    "acceleration_0_100": null,
    "top_speed_kmh": null,
    "length_mm": null,
    "width_mm": null,
    "height_mm": null,
    "wheelbase_mm": null,
    "trunk_volume_l": null,
    "curb_weight_kg": null,
    "drivetrain": null,
    "transmission": null,
    "fuel_consumption_l100km": null,
    "co2_gkm": null,
    "source_url": "https://www.ultimatespecs.com/car-specs/MG/6842/MG-F-160.html",
    "scraped_at": "2026-01-30T06:46:49.227Z"
  },
  {
    "brand": "MG",
    "model": "MG",
    "variant": "MG TF 115",
    "generation": "TF",
    "year_start": 2002,
    "year_end": null,
    "engine_type": null,
    "displacement_cc": null,
    "cylinders": null,
    "power_hp": 115,
    "power_kw": 115,
    "torque_nm": null,
    "acceleration_0_100": null,
    "top_speed_kmh": null,
    "length_mm": null,
    "width_mm": null,
    "height_mm": null,
    "wheelbase_mm": null,
    "trunk_volume_l": null,
    "curb_weight_kg": null,
    "drivetrain": null,
    "transmission": null,
    "fuel_consumption_l100km": null,
    "co2_gkm": null,
    "source_url": "https://www.ultimatespecs.com/car-specs/MG/6850/MG-TF-115.html",
    "scraped_at": "2026-01-30T06:46:50.301Z"
  },
  {
    "brand": "MG",
    "model": "MG",
    "variant": "MG TF 120 Stepspeed",
    "generation": "TF",
    "year_start": 2002,
    "year_end": null,
    "engine_type": null,
    "displacement_cc": null,
    "cylinders": null,
    "power_hp": 120,
    "power_kw": 120,
    "torque_nm": null,
    "acceleration_0_100": null,
    "top_speed_kmh": null,
    "length_mm": null,
    "width_mm": null,
    "height_mm": null,
    "wheelbase_mm": null,
    "trunk_volume_l": null,
    "curb_weight_kg": null,
    "drivetrain": null,
    "transmission": null,
    "fuel_consumption_l100km": null,
    "co2_gkm": null,
    "source_url": "https://www.ultimatespecs.com/car-specs/MG/6848/MG-TF-120-Stepspeed.html",
    "scraped_at": "2026-01-30T06:46:50.301Z"
  },
  {
    "brand": "MG",
    "model": "MG",
    "variant": "MG TF 135",
    "generation": "TF",
    "year_start": 2002,
    "year_end": null,
    "engine_type": null,
    "displacement_cc": null,
    "cylinders": null,
    "power_hp": 136,
    "power_kw": 136,
    "torque_nm": null,
    "acceleration_0_100": null,
    "top_speed_kmh": null,
    "length_mm": null,
    "width_mm": null,
    "height_mm": null,
    "wheelbase_mm": null,
    "trunk_volume_l": null,
    "curb_weight_kg": null,
    "drivetrain": null,
    "transmission": null,
    "fuel_consumption_l100km": null,
    "co2_gkm": null,
    "source_url": "https://www.ultimatespecs.com/car-specs/MG/6849/MG-TF-135.html",
    "scraped_at": "2026-01-30T06:46:50.301Z"
  },
  {
    "brand": "MG",
    "model": "MG",
    "variant": "MG TF 160",
    "generation": "TF",
    "year_start": 2002,
    "year_end": null,
    "engine_type": null,
    "displacement_cc": null,
    "cylinders": null,
    "power_hp": 160,
    "power_kw": 160,
    "torque_nm": null,
    "acceleration_0_100": null,
    "top_speed_kmh": null,
    "length_mm": null,
    "width_mm": null,
    "height_mm": null,
    "wheelbase_mm": null,
    "trunk_volume_l": null,
    "curb_weight_kg": null,
    "drivetrain": null,
    "transmission": null,
    "fuel_consumption_l100km": null,
    "co2_gkm": null,
    "source_url": "https://www.ultimatespecs.com/car-specs/MG/6847/MG-TF-160.html",
    "scraped_at": "2026-01-30T06:46:50.301Z"
  },
  {
    "brand": "MG",
    "model": "MG",
    "variant": "MG XPower SV",
    "generation": "XPower",
    "year_start": 2003,
    "year_end": null,
    "engine_type": null,
    "displacement_cc": null,
    "cylinders": null,
    "power_hp": 324,
    "power_kw": 324,
    "torque_nm": null,
    "acceleration_0_100": null,
    "top_speed_kmh": null,
    "length_mm": null,
    "width_mm": null,
    "height_mm": null,
    "wheelbase_mm": null,
    "trunk_volume_l": null,
    "curb_weight_kg": null,
    "drivetrain": null,
    "transmission": null,
    "fuel_consumption_l100km": null,
    "co2_gkm": null,
    "source_url": "https://www.ultimatespecs.com/car-specs/MG/46201/MG-XPower-SV.html",
    "scraped_at": "2026-01-30T06:46:51.386Z"
  },
  {
    "brand": "MG",
    "model": "MG",
    "variant": "MG RV8 3.9",
    "generation": "RV8",
    "year_start": 1994,
    "year_end": null,
    "engine_type": null,
    "displacement_cc": null,
    "cylinders": null,
    "power_hp": 190,
    "power_kw": 190,
    "torque_nm": null,
    "acceleration_0_100": null,
    "top_speed_kmh": null,
    "length_mm": null,
    "width_mm": null,
    "height_mm": null,
    "wheelbase_mm": null,
    "trunk_volume_l": null,
    "curb_weight_kg": null,
    "drivetrain": null,
    "transmission": null,
    "fuel_consumption_l100km": null,
    "co2_gkm": null,
    "source_url": "https://www.ultimatespecs.com/car-specs/MG/6846/MG-RV8-39.html",
    "scraped_at": "2026-01-30T06:46:52.460Z"
  },
  {
    "brand": "MG",
    "model": "MG",
    "variant": "MG Montego 2000",
    "generation": "Montego",
    "year_start": 2000,
    "year_end": null,
    "engine_type": null,
    "displacement_cc": null,
    "cylinders": null,
    "power_hp": 117,
    "power_kw": 117,
    "torque_nm": null,
    "acceleration_0_100": null,
    "top_speed_kmh": null,
    "length_mm": null,
    "width_mm": null,
    "height_mm": null,
    "wheelbase_mm": null,
    "trunk_volume_l": null,
    "curb_weight_kg": null,
    "drivetrain": null,
    "transmission": null,
    "fuel_consumption_l100km": null,
    "co2_gkm": null,
    "source_url": "https://www.ultimatespecs.com/car-specs/MG/391/MG-Montego-2000.html",
    "scraped_at": "2026-01-30T06:46:53.532Z"
  },
  {
    "brand": "MG",
    "model": "MG",
    "variant": "MG Maestro 1600",
    "generation": "Maestro",
    "year_start": 1983,
    "year_end": null,
    "engine_type": null,
    "displacement_cc": null,
    "cylinders": null,
    "power_hp": 102,
    "power_kw": 102,
    "torque_nm": null,
    "acceleration_0_100": null,
    "top_speed_kmh": null,
    "length_mm": null,
    "width_mm": null,
    "height_mm": null,
    "wheelbase_mm": null,
    "trunk_volume_l": null,
    "curb_weight_kg": null,
    "drivetrain": null,
    "transmission": null,
    "fuel_consumption_l100km": null,
    "co2_gkm": null,
    "source_url": "https://www.ultimatespecs.com/car-specs/MG/390/MG-Maestro-1600.html",
    "scraped_at": "2026-01-30T06:46:54.604Z"
  },
  {
    "brand": "MG",
    "model": "MG",
    "variant": "MG Metro",
    "generation": "Metro",
    "year_start": 1982,
    "year_end": null,
    "engine_type": null,
    "displacement_cc": null,
    "cylinders": null,
    "power_hp": 73,
    "power_kw": 73,
    "torque_nm": null,
    "acceleration_0_100": null,
    "top_speed_kmh": null,
    "length_mm": null,
    "width_mm": null,
    "height_mm": null,
    "wheelbase_mm": null,
    "trunk_volume_l": null,
    "curb_weight_kg": null,
    "drivetrain": null,
    "transmission": null,
    "fuel_consumption_l100km": null,
    "co2_gkm": null,
    "source_url": "https://www.ultimatespecs.com/car-specs/MG/388/MG-Metro-.html",
    "scraped_at": "2026-01-30T06:46:55.689Z"
  },
  {
    "brand": "MG",
    "model": "MG",
    "variant": "MG Metro 6R4 Clubman",
    "generation": "Metro",
    "year_start": 1985,
    "year_end": null,
    "engine_type": null,
    "displacement_cc": null,
    "cylinders": null,
    "power_hp": 253,
    "power_kw": 253,
    "torque_nm": null,
    "acceleration_0_100": null,
    "top_speed_kmh": null,
    "length_mm": null,
    "width_mm": null,
    "height_mm": null,
    "wheelbase_mm": null,
    "trunk_volume_l": null,
    "curb_weight_kg": null,
    "drivetrain": null,
    "transmission": null,
    "fuel_consumption_l100km": null,
    "co2_gkm": null,
    "source_url": "https://www.ultimatespecs.com/car-specs/MG/130107/MG-Metro-6R4-Clubman.html",
    "scraped_at": "2026-01-30T06:46:55.689Z"
  },
  {
    "brand": "MG",
    "model": "MG",
    "variant": "MG Metro Turbo",
    "generation": "Metro",
    "year_start": 1983,
    "year_end": null,
    "engine_type": null,
    "displacement_cc": null,
    "cylinders": null,
    "power_hp": 90,
    "power_kw": 90,
    "torque_nm": null,
    "acceleration_0_100": null,
    "top_speed_kmh": null,
    "length_mm": null,
    "width_mm": null,
    "height_mm": null,
    "wheelbase_mm": null,
    "trunk_volume_l": null,
    "curb_weight_kg": null,
    "drivetrain": null,
    "transmission": null,
    "fuel_consumption_l100km": null,
    "co2_gkm": null,
    "source_url": "https://www.ultimatespecs.com/car-specs/MG/389/MG-Metro-Turbo.html",
    "scraped_at": "2026-01-30T06:46:55.690Z"
  },
  {
    "brand": "MG",
    "model": "MG",
    "variant": "MG B GT",
    "generation": "B",
    "year_start": 1977,
    "year_end": null,
    "engine_type": null,
    "displacement_cc": null,
    "cylinders": null,
    "power_hp": 85,
    "power_kw": 85,
    "torque_nm": null,
    "acceleration_0_100": null,
    "top_speed_kmh": null,
    "length_mm": null,
    "width_mm": null,
    "height_mm": null,
    "wheelbase_mm": null,
    "trunk_volume_l": null,
    "curb_weight_kg": null,
    "drivetrain": null,
    "transmission": null,
    "fuel_consumption_l100km": null,
    "co2_gkm": null,
    "source_url": "https://www.ultimatespecs.com/car-specs/MG/27176/MG-B-GT.html",
    "scraped_at": "2026-01-30T06:46:56.770Z"
  },
  {
    "brand": "MG",
    "model": "MG",
    "variant": "MG B GT V8",
    "generation": "B",
    "year_start": 1973,
    "year_end": null,
    "engine_type": null,
    "displacement_cc": null,
    "cylinders": null,
    "power_hp": 139,
    "power_kw": 139,
    "torque_nm": null,
    "acceleration_0_100": null,
    "top_speed_kmh": null,
    "length_mm": null,
    "width_mm": null,
    "height_mm": null,
    "wheelbase_mm": null,
    "trunk_volume_l": null,
    "curb_weight_kg": null,
    "drivetrain": null,
    "transmission": null,
    "fuel_consumption_l100km": null,
    "co2_gkm": null,
    "source_url": "https://www.ultimatespecs.com/car-specs/MG/15482/MG-B-GT-V8.html",
    "scraped_at": "2026-01-30T06:46:56.770Z"
  },
  {
    "brand": "MG",
    "model": "MG",
    "variant": "MG A 1600 Mk I",
    "generation": "A",
    "year_start": 1959,
    "year_end": null,
    "engine_type": null,
    "displacement_cc": null,
    "cylinders": null,
    "power_hp": 79,
    "power_kw": 79,
    "torque_nm": null,
    "acceleration_0_100": null,
    "top_speed_kmh": null,
    "length_mm": null,
    "width_mm": null,
    "height_mm": null,
    "wheelbase_mm": null,
    "trunk_volume_l": null,
    "curb_weight_kg": null,
    "drivetrain": null,
    "transmission": null,
    "fuel_consumption_l100km": null,
    "co2_gkm": null,
    "source_url": "https://www.ultimatespecs.com/car-specs/MG/20339/MG-A-1600-Mk-I.html",
    "scraped_at": "2026-01-30T06:46:57.848Z"
  },
  {
    "brand": "MG",
    "model": "MG",
    "variant": "MG A 1600 Mk II",
    "generation": "A",
    "year_start": 1961,
    "year_end": null,
    "engine_type": null,
    "displacement_cc": null,
    "cylinders": null,
    "power_hp": 94,
    "power_kw": 94,
    "torque_nm": null,
    "acceleration_0_100": null,
    "top_speed_kmh": null,
    "length_mm": null,
    "width_mm": null,
    "height_mm": null,
    "wheelbase_mm": null,
    "trunk_volume_l": null,
    "curb_weight_kg": null,
    "drivetrain": null,
    "transmission": null,
    "fuel_consumption_l100km": null,
    "co2_gkm": null,
    "source_url": "https://www.ultimatespecs.com/car-specs/MG/20342/MG-A-1600-Mk-II.html",
    "scraped_at": "2026-01-30T06:46:57.848Z"
  },
  {
    "brand": "MG",
    "model": "MG",
    "variant": "MG A Twin Cam",
    "generation": "A",
    "year_start": 1958,
    "year_end": null,
    "engine_type": null,
    "displacement_cc": null,
    "cylinders": null,
    "power_hp": 110,
    "power_kw": 110,
    "torque_nm": null,
    "acceleration_0_100": null,
    "top_speed_kmh": null,
    "length_mm": null,
    "width_mm": null,
    "height_mm": null,
    "wheelbase_mm": null,
    "trunk_volume_l": null,
    "curb_weight_kg": null,
    "drivetrain": null,
    "transmission": null,
    "fuel_consumption_l100km": null,
    "co2_gkm": null,
    "source_url": "https://www.ultimatespecs.com/car-specs/MG/20344/MG-A-Twin-Cam.html",
    "scraped_at": "2026-01-30T06:46:57.848Z"
  }
]